<?xml version="1.0" encoding="utf-8"?>
<!DOCTYPE hibernate-mapping PUBLIC "-//Hibernate/Hibernate Mapping DTD 3.0//EN"
"http://hibernate.sourceforge.net/hibernate-mapping-3.0.dtd">
<!-- 
    Mapping file autogenerated by MyEclipse Persistence Tools
-->
<hibernate-mapping>
    <class name="com.ylink.cim.manage.domain.OrderDetail" table="order_detail" >
        <id name="id" type="java.lang.String">
            <column name="ID" length="20" />
            <generator class="assigned" />
        </id>
        <property name="carModel" type="java.lang.String">
            <column name="car_model" length="50"/>
        </property>
        <property name="productName" type="java.lang.String">
            <column name="product_name" length="50"/>
        </property>
        <property name="num" type="java.lang.Integer">
            <column name="num" />
        </property>
        <property name="material" type="java.lang.String">
            <column name="material" length="50"/>
        </property>
        <property name="color" type="java.lang.String">
            <column name="color" length="10"/>
        </property>
        <property name="price" type="java.lang.Double">
            <column name="price"/>
        </property>
        <property name="amount" type="java.lang.Double">
            <column name="amount"/>
        </property>
        <property name="deliType" type="java.lang.String">
            <column name="deli_type" length="10"/>
        </property>
        <property name="remark" type="java.lang.String">
            <column name="remark" length="25"/>
        </property>
        <property name="orderId" type="java.lang.String">
            <column name="order_id" length="25"/>
        </property>
    </class>
</hibernate-mapping>
